haccks/__init__.py
haccks/example.py
haccks-1.1.dist-info/LICENSE
haccks-1.1.dist-info/METADATA
haccks-1.1.dist-info/WHEEL
haccks-1.1.dist-info/top_level.txt
haccks-1.1.dist-info/RECORD
