Metadata-Version: 2.1
Name: haccks
Version: 1.1
Summary: Hacker Animation Cool Console Kryptographic Sequencer (haccks)
Author: Lucas Parsy
Project-URL: Homepage, https://github.com/LucasParsy/haccks
Project-URL: Issues, https://github.com/LucasParsy/haccks/issues
Classifier: Programming Language :: Python :: 3
Classifier: License :: OSI Approved :: MIT License
Classifier: Operating System :: OS Independent
Requires-Python: >=3.8
License-File: LICENSE
